mdx_headdown/__init__.py
markdown_headdown-0.1.3.dist-info/LICENSE
markdown_headdown-0.1.3.dist-info/METADATA
markdown_headdown-0.1.3.dist-info/WHEEL
markdown_headdown-0.1.3.dist-info/top_level.txt
markdown_headdown-0.1.3.dist-info/RECORD
