Metadata-Version: 2.1
Name: markdown-headdown
Version: 0.1.3
Summary: A Python-Markdown extension to downgrade headings
Home-page: https://github.com/SaschaCowley/Markdown-Headdown
Author: Sascha Cowley
License: UNKNOWN
Keywords: markdown headings downgrade demote lower
Platform: UNKNOWN
Classifier: Programming Language :: Python :: 3
Classifier: License :: OSI Approved :: MIT License
Classifier: Operating System :: OS Independent
Classifier: Development Status :: 4 - Beta
Classifier: Intended Audience :: Developers
Classifier: Topic :: Software Development :: Libraries :: Python Modules 
Classifier: Topic :: Text Processing :: Filters 
Classifier: Topic :: Text Processing :: Markup :: HTML 
Requires-Dist: markdown
